QUANTAXIS/__init__.py
QUANTAXIS/__main__.py
QUANTAXIS/QAAnalysis/QAAnalysis_block.py
QUANTAXIS/QAAnalysis/QAAnalysis_signal.py
QUANTAXIS/QAAnalysis/__init__.py
QUANTAXIS/QACmd/__init__.py
QUANTAXIS/QAData/QABlockStruct.py
QUANTAXIS/QAData/QADataStruct.py
QUANTAXIS/QAData/QAFeatureStruct.py
QUANTAXIS/QAData/QAFinancialStruct.py
QUANTAXIS/QAData/QAIndicatorStruct.py
QUANTAXIS/QAData/QASeriesStruct.py
QUANTAXIS/QAData/__init__.py
QUANTAXIS/QAData/base_datastruct.py
QUANTAXIS/QAData/data_fq.py
QUANTAXIS/QAData/data_marketvalue.py
QUANTAXIS/QAData/data_resample.py
QUANTAXIS/QAData/dsmethods.py
QUANTAXIS/QAData/financial_mean.py
QUANTAXIS/QAData/level2.py
QUANTAXIS/QAData/paneldatastruct.py
QUANTAXIS/QADataBridge/__init__.py
QUANTAXIS/QADataBridge/arrow_converter.py
QUANTAXIS/QADataBridge/shared_memory.py
QUANTAXIS/QAEngine/QAAsyncSchedule.py
QUANTAXIS/QAEngine/QAAsyncTask.py
QUANTAXIS/QAEngine/QAAsyncThread.py
QUANTAXIS/QAEngine/QAEvent.py
QUANTAXIS/QAEngine/QATask.py
QUANTAXIS/QAEngine/QAThreadEngine.py
QUANTAXIS/QAEngine/__init__.py
QUANTAXIS/QAFactor/__init__.py
QUANTAXIS/QAFactor/feature.py
QUANTAXIS/QAFactor/featureAnalysis.py
QUANTAXIS/QAFactor/featureView.py
QUANTAXIS/QAFactor/featurebacktest.py
QUANTAXIS/QAFactor/featurepool.py
QUANTAXIS/QAFetch/Fetcher.py
QUANTAXIS/QAFetch/QABitfinex.py
QUANTAXIS/QAFetch/QABitmex.py
QUANTAXIS/QAFetch/QAClickhouse.py
QUANTAXIS/QAFetch/QACrawler.py
QUANTAXIS/QAFetch/QAEastMoney.py
QUANTAXIS/QAFetch/QAHexun.py
QUANTAXIS/QAFetch/QAJQdata.py
QUANTAXIS/QAFetch/QAKQ.py
QUANTAXIS/QAFetch/QAOKEx.py
QUANTAXIS/QAFetch/QAQAWEB.py
QUANTAXIS/QAFetch/QAQuery.py
QUANTAXIS/QAFetch/QAQuery_Advance.py
QUANTAXIS/QAFetch/QAQuery_Async.py
QUANTAXIS/QAFetch/QATdx.py
QUANTAXIS/QAFetch/QATdx_adv.py
QUANTAXIS/QAFetch/QAThs.py
QUANTAXIS/QAFetch/QATushare.py
QUANTAXIS/QAFetch/QAbinance.py
QUANTAXIS/QAFetch/QAdata.py
QUANTAXIS/QAFetch/QAfinancial.py
QUANTAXIS/QAFetch/QAhuobi.py
QUANTAXIS/QAFetch/QAhuobi_realtime.py
QUANTAXIS/QAFetch/__init__.py
quantaxis_lance-2.1.5a2.dist-info/LICENSE
quantaxis_lance-2.1.5a2.dist-info/METADATA
quantaxis_lance-2.1.5a2.dist-info/WHEEL
quantaxis_lance-2.1.5a2.dist-info/entry_points.txt
quantaxis_lance-2.1.5a2.dist-info/top_level.txt
quantaxis_lance-2.1.5a2.dist-info/RECORD
