Metadata-Version: 2.1
Name: quantaxis-lance
Version: 2.1.5a2
Summary: QUANTAXIS:Quantitative Financial Strategy Framework
Home-page: https://github.com/quantaxis/quantaxis
Author: yutiansut
Author-email: yutiansut@qq.com
License: MIT
Keywords: quantaxis,quant,finance,Backtest,Framework
Platform: UNKNOWN
Classifier: License :: OSI Approved :: MIT License
Classifier: Programming Language :: Python
Classifier: Programming Language :: Python :: 3
Classifier: Programming Language :: Python :: 3.9
Classifier: Programming Language :: Python :: 3.10
Classifier: Programming Language :: Python :: 3.11
Classifier: Programming Language :: Python :: 3.12
Classifier: Intended Audience :: Developers
Classifier: Intended Audience :: Financial and Insurance Industry
Classifier: Operating System :: OS Independent
Classifier: Topic :: Office/Business :: Financial :: Investment
Requires-Python: >=3.9,<4.0
License-File: LICENSE
Requires-Dist: IPython (>=8.12.0)
Requires-Dist: alphalens (>=0.4.0)
Requires-Dist: apscheduler (<4.0.0,>=3.10.0)
Requires-Dist: async-timeout (>=4.0.3)
Requires-Dist: attrs (<24.0.0,>=23.0.0)
Requires-Dist: bs4 (>=0.0.2)
Requires-Dist: clickhouse-cityhash (<2.0.0,>=1.0.2)
Requires-Dist: clickhouse-driver (<0.3.0,>=0.2.9)
Requires-Dist: empyrical (>=0.5.5)
Requires-Dist: flask (<4.0.0,>=3.0.0)
Requires-Dist: gevent-websocket (>=0.10.1)
Requires-Dist: janus (>=1.0.0)
Requires-Dist: jupyter (>=1.0.0)
Requires-Dist: lxml (<6.0.0,>=5.0.0)
Requires-Dist: lz4 (>=4.3.0)
Requires-Dist: matplotlib (>=3.7.0)
Requires-Dist: motor (<4.0.0,>=3.7.0)
Requires-Dist: numba (>=0.59.0)
Requires-Dist: numpy (<2.0.0,>=1.24.0)
Requires-Dist: pandas (<3.0.0,>=2.0.0)
Requires-Dist: pika (<2.0.0,>=1.3.2)
Requires-Dist: protobuf (<6.0.0,>=4.25.0)
Requires-Dist: pyarrow (<18.0.0,>=15.0.0)
Requires-Dist: pyecharts (>=2.0.0)
Requires-Dist: pyecharts-snapshot (>=0.2.0)
Requires-Dist: pyfolio (>=0.9.2)
Requires-Dist: pymongo (<5.0.0,>=4.10.0)
Requires-Dist: pytdx (>=1.72)
Requires-Dist: qaenv (>=0.0.4)
Requires-Dist: qanotify (>=0.0.2)
Requires-Dist: redis (<6.0.0,>=5.2.0)
Requires-Dist: requests (<3.0.0,>=2.32.0)
Requires-Dist: retrying (>=1.3.4)
Requires-Dist: scipy (<2.0.0,>=1.11.0)
Requires-Dist: seaborn (<0.14.0,>=0.13.0)
Requires-Dist: statsmodels (<0.15.0,>=0.14.0)
Requires-Dist: tornado (<7.0.0,>=6.4.0)
Requires-Dist: tushare (>=1.4.0)
Requires-Dist: websocket-client (<2.0.0,>=1.8.0)
Requires-Dist: zenlog (>=1.1)
Provides-Extra: full
Requires-Dist: jupyter (>=1.0.0) ; extra == 'full'
Requires-Dist: jupyterlab (>=4.0.0) ; extra == 'full'
Requires-Dist: msgpack (>=1.1.0) ; extra == 'full'
Requires-Dist: orjson (>=3.10.0) ; extra == 'full'
Requires-Dist: polars (<0.22.0,>=0.20.0) ; extra == 'full'
Requires-Dist: qadataswap (>=0.1.0) ; extra == 'full'
Requires-Dist: qars3 (>=0.0.45) ; extra == 'full'
Provides-Extra: performance
Requires-Dist: msgpack (>=1.1.0) ; extra == 'performance'
Requires-Dist: orjson (>=3.10.0) ; extra == 'performance'
Requires-Dist: polars (<0.22.0,>=0.20.0) ; extra == 'performance'
Provides-Extra: rust
Requires-Dist: qadataswap (>=0.1.0) ; extra == 'rust'
Requires-Dist: qars3 (>=0.0.45) ; extra == 'rust'
